outspin/__init__.py
outspin/constants.py
outspin/exceptions.py
outspin/py.typed
outspin/unix.py
outspin/windows.py
outspin-0.3.2.dist-info/LICENSE
outspin-0.3.2.dist-info/METADATA
outspin-0.3.2.dist-info/WHEEL
outspin-0.3.2.dist-info/RECORD
