Metadata-Version: 2.1
Name: outspin
Version: 0.3.2
Summary: Conveniently read single char inputs in the console.
License: MIT
Author: trag1c
Author-email: trag1cdev@yahoo.com
Requires-Python: >=3.8,<4.0
Classifier: License :: OSI Approved :: MIT License
Classifier: Programming Language :: Python :: 3
Classifier: Programming Language :: Python :: 3.8
Classifier: Programming Language :: Python :: 3.9
Classifier: Programming Language :: Python :: 3.10
Classifier: Programming Language :: Python :: 3.11
Classifier: Programming Language :: Python :: 3.12
